paraphraser.py
paraphraser-0.0.1.dist-info/LICENSE.txt
paraphraser-0.0.1.dist-info/METADATA
paraphraser-0.0.1.dist-info/WHEEL
paraphraser-0.0.1.dist-info/top_level.txt
paraphraser-0.0.1.dist-info/RECORD
