Metadata-Version: 2.1
Name: paraphraser
Version: 0.0.1
Summary: A python module which returns list of sentences with same contextual meaning as given sentence
Home-page: https://github.com/17shashank17/Paraphraser
Author: Shashank Jaiswal
Author-email: 17shashank17@gmail.com
License: UNKNOWN
Platform: UNKNOWN
Classifier: Programming Language :: Python :: 2.7
Classifier: Programming Language :: Python :: 3
Classifier: Programming Language :: Python :: 3.6
Classifier: Programming Language :: Python :: 3.7
Classifier: License :: OSI Approved :: GNU General Public License v2 or later (GPLv2+)
Classifier: Operating System :: OS Independent
Requires-Dist: googletrans (~=3.0.0)
Provides-Extra: dev
Requires-Dist: pytest (>=3.7) ; extra == 'dev'
Requires-Dist: twine (~=3.2.0) ; extra == 'dev'
